{
  "id": "3426124",
  "name": "test",
  "font_family": "iconfont",
  "css_prefix_text": "icon-",
  "description": "",
  "glyphs": [
    {
      "icon_id": "29188782",
      "name": "吐槽",
      "font_class": "tucao",
      "unicode": "ed17",
      "unicode_decimal": 60695
    },
    {
      "icon_id": "29188935",
      "name": "评论",
      "font_class": "pinglun",
      "unicode": "ed18",
      "unicode_decimal": 60696
    },
    {
      "icon_id": "29188949",
      "name": "钱币",
      "font_class": "qianbi",
      "unicode": "ed19",
      "unicode_decimal": 60697
    },
    {
      "icon_id": "29189081",
      "name": "我的",
      "font_class": "wode",
      "unicode": "ed1a",
      "unicode_decimal": 60698
    },
    {
      "icon_id": "29189283",
      "name": "我的2",
      "font_class": "wode2",
      "unicode": "ed1b",
      "unicode_decimal": 60699
    },
    {
      "icon_id": "29189549",
      "name": "我的3",
      "font_class": "wode3",
      "unicode": "ed1c",
      "unicode_decimal": 60700
    },
    {
      "icon_id": "29201544",
      "name": "订单",
      "font_class": "dingdan",
      "unicode": "ed1e",
      "unicode_decimal": 60702
    },
    {
      "icon_id": "29201945",
      "name": "首页3",
      "font_class": "shouye3",
      "unicode": "ed21",
      "unicode_decimal": 60705
    }
  ]
}
